LICENSE
wolproxypycli/__init__.py
wolproxypycli/__main__.py
wolproxypycli/main.py
wolproxypycli-0.1.9.dist-info/LICENSE
wolproxypycli-0.1.9.dist-info/METADATA
wolproxypycli-0.1.9.dist-info/WHEEL
wolproxypycli-0.1.9.dist-info/entry_points.txt
wolproxypycli-0.1.9.dist-info/RECORD
