Metadata-Version: 2.1
Name: wolproxypycli
Version: 0.1.9
Summary: A PyPI module and Typer (CLI) app for sending Wake-On-LAN packets
License: MIT
Author: Fabio Calefato
Author-email: fabio.calefato@uniba.it
Requires-Python: >=3.12,<4.0
Classifier: License :: OSI Approved :: MIT License
Classifier: Programming Language :: Python :: 3
Classifier: Programming Language :: Python :: 3.12
Requires-Dist: poetry-plugin-export (>=1.6.0,<2.0.0)
Requires-Dist: pretty-errors (>=1.2.25,<2.0.0)
Requires-Dist: rich (>=13.7.0,<14.0.0)
Requires-Dist: typer (>=0.9.0,<0.10.0)
Requires-Dist: wakeonlan (>=3.1.0,<4.0.0)
